{
  "ApplicationTheme": "Dark",
  "OpenInPresentationMode": true,
  "UseSingleWindow": true,
  "EditorTheme": "vscodedark",
  "Editor": {
    "Font": "Consolas",
    "FontSize": 16,
    "LineHeight": 1.45,
    "CenteredMode": true,
    "CenteredModeMaxWidth": 970,
    "Padding": 20,
    "ZoomLevel": 100,
    "EditorPreviewFlowDirection": "LeftToRight",
    "HighlightActiveLine": true,
    "ShowLineNumbers": false,
    "ShowInvisibles": false,
    "LinefeedMode": "Lf",
    "NoAutoComplete": false,
    "TablePasteMode": "PipeTable",
    "TableEditorDefaultCsvImportSymbol": ",",
    "EnableSpellcheck": true,
    "Dictionary": "en-US",
    "TabSize": 4,
    "UseSoftTabs": true,
    "WrapText": true,
    "WrapMargin": 0,
    "ClickableLinks": true,
    "ShowPrintMargin": false,
    "PrintMargin": 0,
    "KeyboardHandler": "default",
    "EnableRightToLeft": false,
    "EnableBulletAutoCompletion": false,
    "AdditionalToolbarIcons": {},
    "PreviewHighlightTimeout": 1800
  },
  "Preview": {
    "PreviewTheme": "Github Dark",
    "PreviewSyncMode": "EditorToPreview",
    "PreviewMode": "InternalPreview",
    "PreviewHttpLinksExternal": true,
    "PreviewBackgroundColorOverride": null
  },
  "TitlebarDisplay": "FilenameOnly",
  "DistractionFreeModeHideOptions": "toolbar,statusbar,menu,preview,tabs,maximized,maxwidth:960",
  "AutoSaveDocuments": false,
  "AutoSaveBackups": true,
  "AlwaysUsePreviewRefresh": false,
  "DefaultCodeSyntax": "csharp",
  "WebBrowserPreviewExecutable": null,
  "WebBrowserSearchEngine": "DuckDuckGo",
  "OpenFolderCommand": "explorer.exe",
  "TerminalCommand": "powershell.exe",
  "TerminalCommandArgs": "-noexit -command \"cd '{0}'\"",
  "OpenDocuments": [],
  "RecentDocuments": [],
  "RecentDocumentsLength": 10,
  "RememberNumberOfLastDocuments": 5,
  "Images": {
    "ImageEditor": "C:\\Program Files\\irfanview\\i_view64.exe",
    "ImageViewer": null,
    "JpegImageCompressionLevel": 80,
    "LastImageWidth": 970,
    "LastImageHeight": 700
  },
  "Markdown": {
    "AutoLinks": true,
    "AutoHeaderIdentifiers": true,
    "StripYamlFrontMatter": true,
    "UseTables": true,
    "FootersAndFootnotes": true,
    "ListExtras": true,
    "EmojiAndSmiley": true,
    "MediaLinks": true,
    "Figures": true,
    "GithubTaskLists": true,
    "UseMathematics": true,
    "MermaidDiagrams": true,
    "UsePlantUml": true,
    "PlantUmlServerUrl": "http://www.plantuml.com/plantuml/png/",
    "Abbreviations": true,
    "CustomContainers": true,
    "GenericAttributes": true,
    "SmartyPants": false,
    "NoHtml": false,
    "RenderLinksAsExternal": false,
    "ItalicSymbol": "*",
    "SoftReturnSymbol": "  ",
    "MarkdigExtensions": "",
    "AllowRenderScriptTags": true,
    "MarkdownParserName": "MarkDig",
    "ParseDocFx": true,
    "MarkdownLinting": false,
    "MarkdownSymbols": {},
    "MermaidDiagramsUrl": "https://cdn.jsdelivr.net/npm/mermaid/dist/mermaid.min.js"
  },
  "EditorExtensionMappings": {
    "md": "markdown",
    "markdown": "markdown",
    "mdcrypt": "markdown",
    "mdown": "markdown",
    "mkd": "markdown",
    "mkdn": "markdown",
    "json": "json",
    "kavadocs": "json",
    "mdproj": "json",
    "html": "html",
    "htm": "html",
    "cs": "csharp",
    "fs": "fsharp",
    "js": "javascript",
    "ts": "typescript",
    "dart": "dart",
    "css": "css",
    "less": "less",
    "sass": "sass",
    "sql": "sqlserver",
    "prg": "foxpro",
    "vb": "vb",
    "py": "python",
    "c": "c_cpp",
    "cpp": "c_cpp",
    "ps1": "powershell",
    "sh": "sh",
    "bash": "sh",
    "bat": "batchfile",
    "cmd": "batchfile",
    "asp": "html",
    "aspx": "html",
    "jsx": "jsx",
    "php": "php",
    "go": "golang",
    "cshtml": "razor",
    "vbhtml": "razor",
    "razor": "razor",
    "r": "r",
    "mak": "makefile",
    "xml": "xml",
    "xaml": "xml",
    "wsdl": "xml",
    "config": "xml",
    "ini": "ini",
    "user": "xml",
    "dotsettings": "xml",
    "csproj": "xml",
    "sln": "xml",
    "nuspec": "xml",
    "yaml": "yaml",
    "dockerfile": "dockerfile",
    "yml": "yaml",
    "diff": "diff",
    "txt": "text",
    "log": "text",
    "reg": "text"
  },
  "ExternalPrograms": [],
  "ApplicationUpdates": {
    "LastUpdateCheck": "2024-09-30T06:27:19.3574088Z",
    "UpdateFrequency": 7,
    "AccessCount": 0,
    "FirstRun": false
  },
  "WindowPosition": {
    "Top": 0,
    "Left": 20,
    "Width": 1100,
    "Height": 1040,
    "InternalPreviewWidth": 720,
    "PreviewTop": 0,
    "PreviewLeft": 0,
    "PreviewHeight": 700,
    "TableEditorLeft": 0,
    "TableEditorTop": 0,
    "TableEditorWidth": 0,
    "TableEditorHeight": 0,
    "PreviewWidth": 720,
    "PreviewDisplayMode": "ActivatedByMainWindow",
    "PreviewDocked": false,
    "SplitterPosition": 600,
    "RightSidebardWidth": 250,
    "ConsolePanelHeight": 100.0,
    "IsTabHeaderPanelVisible": true,
    "WindowState": "Normal",
    "WindowPresets": [
      "2500 x 1750,1050,350",
      "2250 x 1500,920,330",
      "1900 x 1020,730,310",
      "1600 x 850,600,300",
      "1250 x 760,445,270",
      "950 x 620,445,0",
      "770 x 560,380,0"
    ]
  },
  "FolderBrowser": {
    "WindowWidth": 195,
    "Visible": true,
    "FolderPath": null,
    "IgnoredFolders": ".git,node_modules,.vs,.idea",
    "IgnoredFileExtensions": ".saved.bak,kavadocstopic.md,.saved.bak.md",
    "ShowAllFiles": false,
    "RecentFolders": [],
    "ShowIcons": true,
    "MarkdownPreviewMode": "EditorPreview",
    "DoubleClickDelay": 300,
    "TrackDocumentInFolderBrowser": false,
    "ShowToolTips": true,
    "FileOrder": "Name",
    "SearchInSubFolders": false
  },
  "Git": {
    "GitCommitBehavior": "CommitAndPush",
    "CloseAfterCommit": true,
    "GitClientExecutable": "C:\\Users\\tatka\\AppData\\Local\\gitkraken\\app-9.0.1\\gitkraken.exe",
    "GitDiffExecutable": "C:\\Program Files\\Microsoft VS Code\\Code.exe",
    "GitName": null,
    "GitEmail": null
  },
  "PdfOutputWindow": {
    "Title": null,
    "PageSize": "Letter",
    "Orientation": "Portrait",
    "FooterText": "Page [page] of [topage]",
    "ImageDpi": 300,
    "GenerateTableOfContents": true,
    "DisplayPdfAfterGeneration": true,
    "Margins": {
      "MarginLeft": 0,
      "MarginRight": 0,
      "MarginTop": 0,
      "MarginBottom": 0
    },
    "PdfPreviewTheme": "Pdf Output"
  },
  "WebServer": {
    "Port": 5009,
    "AutoStart": false
  },
  "System": {
    "DisableHardwareAcceleration": false,
    "ShowPreviewDeveloperTools": false,
    "ShowPreviewDeveloperToolsOnStartup": false,
    "ShowEditorDeveloperTools": false,
    "DebugEditorHtmlTemplatesPath": ".\\Editor",
    "DebugPreviewHtmlTemplatesPath": ".\\PreviewThemes",
    "IgnoreWebViewVersionMismatch": false,
    "ReportErrors": true,
    "SendTelemetry": true
  },
  "Experimental": {
    "EnableCommandPalette": true
  },
  "IsPreviewVisible": true,
  "IsDocumentOutlineVisible": true,
  "MaxDocumentOutlineLevel": 4,
  "DisableAddins": false,
  "DisableSplashScreen": false,
  "ShowVersionNumberInTitle": false,
  "StatusMessageTimeout": 8000,
  "ShowGeneratedOutputInShell": false,
  "LastLinkExternal": false,
  "LastUseReferenceLinks": false,
  "LastLinkFolder": null,
  "LastFolder": "untitled",
  "CommonFolder": "E:\\Projekty\\zEasy\\GITHUB-PROJECTS\\EICESB-MODULES\\MarkDownMonster\\MarkdownMonsterPortable\\PortableSettings",
  "LocalAppDataFolder": "C:\\Users\\tatka\\AppData\\Local\\Markdown Monster"
}